mcp_server_gravitino/__init__.py
mcp_server_gravitino/utils.py
mcp_server_gravitino/server/__init__.py
mcp_server_gravitino/server/__main__.py
mcp_server_gravitino/server/app.py
mcp_server_gravitino/server/main.py
mcp_server_gravitino/server/settings.py
mcp_server_gravitino/server/tools/__init__.py
mcp_server_gravitino/server/tools/catalog.py
mcp_server_gravitino/server/tools/common_tools.py
mcp_server_gravitino/server/tools/models.py
mcp_server_gravitino/server/tools/schema.py
mcp_server_gravitino/server/tools/table.py
mcp_server_gravitino/server/tools/tag.py
mcp_server_gravitino/server/tools/user_role.py
mcp_server_gravitino-0.1.0.dist-info/METADATA
mcp_server_gravitino-0.1.0.dist-info/WHEEL
mcp_server_gravitino-0.1.0.dist-info/entry_points.txt
mcp_server_gravitino-0.1.0.dist-info/licenses/LICENSE
mcp_server_gravitino-0.1.0.dist-info/RECORD
