Metadata-Version: 2.4
Name: mcp-server-gravitino
Version: 0.1.0
Summary: MCP server providing Gravitino APIs
Project-URL: Homepage, https://github.com/datastrato/mcp-server-gravitino
Project-URL: Repository, https://github.com/datastrato/mcp-server-gravitino
Project-URL: Documentation, https://github.com/datastrato/mcp-server-gravitino#readme
Project-URL: Bug Tracker, https://github.com/datastrato/mcp-server-gravitino/issues
License: MIT
License-File: LICENSE
Keywords: Gravitino,fastmcp,integration,mcp,metadata
Requires-Python: >=3.10
Requires-Dist: fastmcp>=2.2.7
Requires-Dist: httpx>=0.28.1
Requires-Dist: pydantic-settings>=2.8.1
